docs/source/conf.py
pvlive_api/__init__.py
pvlive_api/pvlive.py
tests/test_pvlive_api.py
pvlive_api-1.4.0.dist-info/METADATA
pvlive_api-1.4.0.dist-info/WHEEL
pvlive_api-1.4.0.dist-info/entry_points.txt
pvlive_api-1.4.0.dist-info/top_level.txt
pvlive_api-1.4.0.dist-info/RECORD
