Metadata-Version: 2.1
Name: pvlive_api
Version: 1.4.0
Summary: A Python interface for the PV_Live web API from Sheffield Solar.
Author-email: Jamie Taylor <jamie.taylor@sheffield.ac.uk>
Maintainer-email: Jamie Taylor <jamie.taylor@sheffield.ac.uk>
Project-URL: Homepage, https://www.solar.sheffield.ac.uk/pvlive/
Project-URL: Documentation, https://sheffieldsolar.github.io/PV_Live-API/build/html/index.html
Project-URL: Repository, https://github.com/SheffieldSolar/PV_Live-API
Project-URL: Bug Tracker, https://github.com/SheffieldSolar/PV_Live-API/issues
Keywords: solar,pv,pv_live,api
Classifier: Development Status :: 4 - Beta
Classifier: Intended Audience :: Developers
Classifier: Intended Audience :: Science/Research
Classifier: Intended Audience :: System Administrators
Classifier: Topic :: Database :: Database Engines/Servers
Classifier: Topic :: Utilities
Classifier: Programming Language :: Python
Classifier: Programming Language :: Python :: 3
Classifier: Programming Language :: Python :: 3.10
Classifier: Programming Language :: Python :: 3.11
Classifier: Programming Language :: Python :: 3.12
Requires-Python: >=3.10
Requires-Dist: pytz
Requires-Dist: requests
Requires-Dist: numpy
Requires-Dist: pandas
Requires-Dist: bs4
